Dff/Dff.sv
module Dff(
input [31:0]d,
input clk, reset,
output reg [31:0]q
);
always@(posedge clk) 
begin
if(reset== 1)
q <= 0;
else 
q <= d;  
end 
endmodule

Mux/Mux.sv
module Mux(
output [31:0] Y,
input [31:0] D0, D1,
input S
);

assign Y=(S)?D1:D0;

endmodule

adder/adder.v
module adder(input [31:0]a,b,
            output [31:0]out);

assign out = a+b;
endmodule

data_memory/data_memory.v
module data_memory(input [31:0]A,//address 
                    input [31:0]WD,//data
                    input WE,clk,//write enalble , clock
                    output reg [31:0]RD
                    );
reg [31:0]register[31:0];
always@(posedge clk)
begin
  if(WE)
    register[A]<=WD;
  else
    RD<=register[A];
end
endmodule

extend/extend.v
module extend(
    input [31:0] instr,
    input [1:0] ImmSrc,
    output reg [31:0] ImmExt
);

always @(*) begin
    case (ImmSrc)
        2'b00: ImmExt = {{20{instr[31]}}, instr[31:20]};   // I-type
        2'b01: ImmExt = {{20{instr[31]}}, instr[31:25], instr[11:7]};  // S-type
        2'b10: ImmExt = {{12{instr[31]}}, instr[19:12], instr[20], instr[30:21], 1'b0}; // B-type
        default: ImmExt = 32'd0; // R-type
        endcase
end

endmodule

ALU/ALU.v
`define ADD 4'b0000
`define SUB 4'b1000
`define SLL 4'b0001
`define SLT 4'b0010
`define SLTU 4'b0011
`define XOR 4'b0100
`define SRL 4'b0101
`define SRA 4'b1101
`define OR 4'b0110
`define AND 4'b0111 
module ALU (input [31:0]SrcA,SrcB,
        input [3:0]ALUControl,
        input reset,
        output reg [31:0]ALUResult,
        output reg Zero
        );

always @ (posedge reset)
begin
  ALUResult<=0;
  Zero<=0;
end

always @ (SrcA or SrcB or ALUControl)
begin
    case(ALUControl)
      `ADD:ALUResult<=SrcA+SrcB;
      `SUB:ALUResult<=SrcA-SrcB;
      `SLL:ALUResult<=SrcA<<SrcB;
      `SLT:ALUResult<=(SrcA < SrcB) ? 32'b1 :32'b0;
      `SLTU:ALUResult<=(SrcA < SrcB) ? 32'b1 :32'b0;
      `XOR:ALUResult<=SrcA^SrcB;
      `SRL:ALUResult<=(SrcA>>SrcB);
      `SRA:ALUResult<=SrcA<<<SrcB;
      `OR:ALUResult<=SrcA|SrcB;
      `AND :ALUResult<=SrcA&SrcB;
    endcase
  if (ALUResult==0)
    Zero<=1;
  else 
    Zero<=0;
end
endmodule

Control/Control.v
module controlUnit(input  [6:0]op,
                input [2:0]funct3,
                input funct7,zero,
                output reg  PCSrc,ResultSrc,MemWrite,ALUSrc,RegWrite,
                output reg [3:0]ALUControl,
                output reg [1:0]ImmSrc);

localparam [6:0]R_TYPE  = 7'b0110011,
                I_TYPE  = 7'b0010011,
                S_TYPE  = 7'b0100011,
                LOAD    = 7'b0000011,
                BRANCH  = 7'b1100011,
                JALR    = 7'b1100111,
                JAL     = 7'b1101111;

reg branch;
always @(funct3,funct7,op,zero) begin
    case (op)
        //R-Type instruction
        R_TYPE :begin
            RegWrite <= 1;
            MemWrite <= 0;
            ResultSrc <= 2'b00;
            PCSrc <= 0;
            ALUSrc<=0;
        end

        LOAD :begin
            MemWrite<=0;
            RegWrite<=1;
            ALUControl<=4'b0000;
            ImmSrc<=2'b00;
            ALUSrc<=1;
            ResultSrc<=2'b01;
            PCSrc <= 0;
        end

        S_TYPE :begin
            MemWrite<=1;
            RegWrite<=0;
            ALUControl<=4'b0000;
            ImmSrc<=2'b01;
            ALUSrc<=1;
            PCSrc <= 0;
        end

        BRANCH :begin
            MemWrite<=0;
            RegWrite<=0;
            ALUControl<=4'b0001;
            ImmSrc<=2'b10;
            ALUSrc<=0;
            branch <= 1;
            PCSrc <= branch & zero;
        end

        JAL :begin
            MemWrite<=0;
            RegWrite<=1;
            ImmSrc<=2'b11;
            branch <= 0;
            ResultSrc<=2'b10;
            end

        I_TYPE :begin
            RegWrite <= 1;
            MemWrite <= 0;
            ImmSrc<=2'b00;
            ALUSrc <= 1;
            ResultSrc <= 2'b00;
            end
    endcase
end
always@(funct3,funct7,op,zero)
  ALUControl = {funct7, funct3};

endmodule

Registers/Register.v
// Stuff left :setup the special registers such as CPSR ,LR ,etc
module registers(
    input [4:0] A1,A2,A3,
    input [31:0] WD3,
    input WE3,reset,clk,
    output reg [31:0]RD1,RD2
);
    integer i;
    reg [31:0] register [31:0]; reg CPSR, LR; 
    always @(posedge reset) begin 
      for (i=0;i<32;i=i+1)
            begin
                register[i] <= 32'h0; 
            end  
        RD1<=0;
        RD2<=0;
    end
    // The register file will always output the vaules corresponding to read register numbers 
    // It is independent of any other signal
    always @(posedge clk)
    begin
        if(!WE3)
            begin
                RD1 <= register[A1];
                RD2 <= register[A2];
            end
        else
            begin
                register[A3]<=WD3;
            end
    end
endmodule

instruction_memory/instruction_memory.v

module instruction_memory(
    input [31:0] A,
    input reset,
    output [31:0] RD
);
    reg [7:0] Memory [31:0]; // Byte addressable memory with 32 locations

    // Under normal operation (reset = 1), we assign the instr. code, based on A
    assign RD = {Memory[A+3], Memory[A+2], Memory[A+1], Memory[A]};

    // Initializing memory when reset is zero
    always @(posedge reset) // Use negedge or posedge depending on your requirements
    begin
        if(reset)
        begin
          //stack 0 FFC4A303 load
            Memory[3] = 8'hFF;
            Memory[2] = 8'hC4;
            Memory[1] = 8'hA3;
            Memory[0] = 8'h03;
            //stack 1 0064A423 Sw
            Memory[7] = 8'h00;
            Memory[6] = 8'h64;
            Memory[5] = 8'hA4;
            Memory[4] = 8'h23;
            //stack 2 0062E233 0r
            Memory[11] = 8'h00;
            Memory[10] = 8'h62;
            Memory[9] = 8'hE2;
            Memory[8] = 8'h33;
            //stack 3 FE420AE3 Beq
            Memory[15] = 8'hFE;
            Memory[14] = 8'h42;
            Memory[13] = 8'h0A;
            Memory[12] = 8'hE3;
            //stack 4 02728863 JAL
            Memory[19] = 8'h02;
            Memory[18] = 8'h72;
            Memory[17] = 8'h88;
            Memory[16] = 8'h63;
            //stack 5
            Memory[23] = 8'h00;
            Memory[22] = 8'h00;
            Memory[21] = 8'h00;
            Memory[20] = 8'h00;
            //stack 6
            Memory[27] = 8'h00;
            Memory[26] = 8'h00;
            Memory[25] = 8'h00;
            Memory[24] = 8'h00;
            //stack 7
            Memory[31] = 8'h00;
            Memory[30] = 8'h00;
            Memory[29] = 8'h00;
            Memory[28] = 8'h00;
         end
    end

endmodule

top/top.v
`include "../ALU/ALU.v"
`include "../data_memory/data_memory.v"
`include "../Registers/Register.v"
`include "../adder/adder.v"
`include "../Dff/Dff.sv"
`include "../Mux/Mux.sv"
`include "../extend/extend.v"
`include "../Control/Control.v"
`include "../instruction_memory/instruction_memory.v"
module top(input clk,reset);
wire [31:0]Result;
wire [31:0] PC;
wire PCSrc;
wire [31:0]instr;
wire ResultSrc,MemWrite,ALUSrc,RegWrite;
wire [1:0]ImmSrc;
wire [3:0]ALUControl;
wire [31:0] SrcA,SrcB;
wire [31:0] WriteData,ImmExt,ALUResult;
wire Zero;
wire [31:0] ReadData;
wire [31:0] PCTarget,PCPlus4,PCNext;


instruction_memory inst_mem (
  .A(PC),
  .reset(reset),
  .RD(instr)
);

registers register (
  .A1(instr[19:15]),
  .A2(instr[24:20]),
  .A3(instr[11:7]),
  .clk(clk),
  .WD3(Result),
  .RD1(SrcA),
  .RD2(WriteData),
  .WE3(RegWrite),
  .reset(reset)
);
controlUnit control(
  .op(instr[6:0]),
  .funct3(instr[14:12]),
  .funct7(instr[30]),
  .zero(Zero),
  .PCSrc(PCSrc),
  .ResultSrc(ResultSrc),
  .MemWrite(MemWrite),
  .ALUSrc(ALUSrc),
  .RegWrite(RegWrite),
  .ALUControl(ALUControl),
  .ImmSrc(ImmSrc)
);

ALU alu(
  .SrcA(SrcA),
  .SrcB(SrcB),
  .ALUControl(ALUControl),
  .reset(reset),
  .Zero(Zero),
  .ALUResult(ALUResult)
);

extend extender(
  .instr(instr),
  .ImmSrc(ImmSrc),
  .ImmExt(ImmExt)
);
Mux mux_alu(
  .D0(WriteData),
  .D1(ImmExt),
  .S(ALUSrc),
  .Y(SrcB)
);

data_memory datamem (
  .A(ALUResult),
  .WD(WriteData),
  .RD(ReadData),
  .WE(MemWrite),
  .clk(clk)
);

Mux mux_dataMem (
  .D0(ALUResult),
  .D1(ReadData),
  .S(ResultSrc),
  .Y(Result)
);

adder adder_branch (
  .a(PC),
  .b(ImmExt),
  .out(PCTarget)
);

adder adder_PC (
  .a(PC),
  .b(32'd4),
  .out(PCPlus4)
);

Mux mux_PC (
  .D0(PCPlus4),
  .D1(PCTarget),
  .S(PCSrc),
  .Y(PCNext)
);

Dff dff (
  .d(PCNext),
  .q(PC),
  .clk(clk),
  .reset(reset)
);
endmodule

top/top_tb.v
`include "top.v"
module top_tb();

reg clk,reset;

top uut (.clk(clk),.reset(reset));
always 
begin
  #5 clk = ~ clk;
end
initial
begin
  clk =1;
  reset = 1;
  #10;
  reset = 0; #100;
  $finish;
end

initial 
begin
  $dumpfile("waves.vcd");
  $dumpvars();
end
endmodule

top/waves.vcd
$date
	Mon Aug 12 11:24:56 2024
$end
$version
	Icarus Verilog
$end
$timescale
	1s
$end
$scope module top_tb $end
$var reg 1 ! clk $end
$var reg 1 " reset $end
$scope module uut $end
$var wire 1 ! clk $end
$var wire 1 " reset $end
$var wire 32 # instr [31:0] $end
$var wire 1 $ Zero $end
$var wire 32 % WriteData [31:0] $end
$var wire 32 & SrcB [31:0] $end
$var wire 32 ' SrcA [31:0] $end
$var wire 1 ( ResultSrc $end
$var wire 32 ) Result [31:0] $end
$var wire 1 * RegWrite $end
$var wire 32 + ReadData [31:0] $end
$var wire 32 , PCTarget [31:0] $end
$var wire 1 - PCSrc $end
$var wire 32 . PCPlus4 [31:0] $end
$var wire 32 / PCNext [31:0] $end
$var wire 32 0 PC [31:0] $end
$var wire 1 1 MemWrite $end
$var wire 2 2 ImmSrc [1:0] $end
$var wire 32 3 ImmExt [31:0] $end
$var wire 1 4 ALUSrc $end
$var wire 32 5 ALUResult [31:0] $end
$var wire 4 6 ALUControl [3:0] $end
$scope module adder_PC $end
$var wire 32 7 b [31:0] $end
$var wire 32 8 out [31:0] $end
$var wire 32 9 a [31:0] $end
$upscope $end
$scope module adder_branch $end
$var wire 32 : out [31:0] $end
$var wire 32 ; b [31:0] $end
$var wire 32 < a [31:0] $end
$upscope $end
$scope module alu $end
$var wire 1 " reset $end
$var wire 32 = SrcB [31:0] $end
$var wire 32 > SrcA [31:0] $end
$var wire 4 ? ALUControl [3:0] $end
$var reg 32 @ ALUResult [31:0] $end
$var reg 1 $ Zero $end
$upscope $end
$scope module control $end
$var wire 3 A funct3 [2:0] $end
$var wire 1 B funct7 $end
$var wire 7 C op [6:0] $end
$var wire 1 $ zero $end
$var parameter 7 D BRANCH $end
$var parameter 7 E I_TYPE $end
$var parameter 7 F JAL $end
$var parameter 7 G JALR $end
$var parameter 7 H LOAD $end
$var parameter 7 I R_TYPE $end
$var parameter 7 J S_TYPE $end
$var reg 4 K ALUControl [3:0] $end
$var reg 1 4 ALUSrc $end
$var reg 2 L ImmSrc [1:0] $end
$var reg 1 1 MemWrite $end
$var reg 1 - PCSrc $end
$var reg 1 * RegWrite $end
$var reg 1 ( ResultSrc $end
$var reg 1 M branch $end
$upscope $end
$scope module datamem $end
$var wire 32 N A [31:0] $end
$var wire 1 1 WE $end
$var wire 1 ! clk $end
$var wire 32 O WD [31:0] $end
$var reg 32 P RD [31:0] $end
$upscope $end
$scope module dff $end
$var wire 1 ! clk $end
$var wire 1 " reset $end
$var wire 32 Q d [31:0] $end
$var reg 32 R q [31:0] $end
$upscope $end
$scope module extender $end
$var wire 2 S ImmSrc [1:0] $end
$var wire 32 T instr [31:0] $end
$var reg 32 U ImmExt [31:0] $end
$upscope $end
$scope module inst_mem $end
$var wire 32 V A [31:0] $end
$var wire 1 " reset $end
$var wire 32 W RD [31:0] $end
$upscope $end
$scope module mux_PC $end
$var wire 32 X D0 [31:0] $end
$var wire 32 Y D1 [31:0] $end
$var wire 1 - S $end
$var wire 32 Z Y [31:0] $end
$upscope $end
$scope module mux_alu $end
$var wire 32 [ D1 [31:0] $end
$var wire 1 4 S $end
$var wire 32 \ Y [31:0] $end
$var wire 32 ] D0 [31:0] $end
$upscope $end
$scope module mux_dataMem $end
$var wire 32 ^ D0 [31:0] $end
$var wire 32 _ D1 [31:0] $end
$var wire 1 ( S $end
$var wire 32 ` Y [31:0] $end
$upscope $end
$scope module register $end
$var wire 5 a A1 [4:0] $end
$var wire 5 b A2 [4:0] $end
$var wire 5 c A3 [4:0] $end
$var wire 32 d WD3 [31:0] $end
$var wire 1 * WE3 $end
$var wire 1 ! clk $end
$var wire 1 " reset $end
$var reg 32 e RD1 [31:0] $end
$var reg 32 f RD2 [31:0] $end
$var integer 32 g i [31:0] $end
$upscope $end
$upscope $end
$upscope $end
$enddefinitions $end
$comment Show the parameter values. $end
$dumpall
b100011 J
b110011 I
b11 H
b1100111 G
b1101111 F
b10011 E
b1100011 D
$end
#0
$dumpvars
b100000 g
b0 f
b0 e
bx d
b110 c
b11100 b
b1001 a
bx `
bx _
b11111111111111111111111111111100 ^
b0 ]
b11111111111111111111111111111100 \
b11111111111111111111111111111100 [
b100 Z
b11111111111111111111111111111100 Y
b100 X
b11111111110001001010001100000011 W
b0 V
b11111111111111111111111111111100 U
b11111111110001001010001100000011 T
b0 S
b0 R
b100 Q
bx P
b0 O
b11111111111111111111111111111100 N
xM
b0 L
b0 K
b11 C
1B
b10 A
b11111111111111111111111111111100 @
b0 ?
b0 >
b11111111111111111111111111111100 =
b0 <
b11111111111111111111111111111100 ;
b11111111111111111111111111111100 :
b0 9
b100 8
b100 7
b0 6
b11111111111111111111111111111100 5
14
b11111111111111111111111111111100 3
b0 2
01
b0 0
b100 /
b100 .
0-
b11111111111111111111111111111100 ,
bx +
1*
bx )
1(
b0 '
b11111111111111111111111111111100 &
b0 %
1$
b11111111110001001010001100000011 #
1"
1!
$end
#5
0!
#10
0$
b1000 5
b1000 @
b1000 N
b1000 ^
b1 2
b1 L
b1 S
0*
11
b0 6
b0 ?
b0 K
b1000 &
b1000 =
b1000 \
0B
b110 b
b1000 c
b100011 C
b1000 3
b1000 ;
b1000 U
b1000 [
b1000 /
b1000 Q
b1000 Z
b11001001010010000100011 #
b11001001010010000100011 T
b11001001010010000100011 W
b1100 ,
b1100 :
b1100 Y
b1000 .
b1000 8
b1000 X
b100 0
b100 9
b100 <
b100 R
b100 V
1!
0"
#15
0!
#20
bx )
bx `
bx d
bx 5
bx @
bx N
bx ^
04
0(
01
1*
b110 6
b110 ?
b110 K
bx &
bx =
bx \
b101 a
b110 A
b100 c
b110011 C
b100 3
b100 ;
b100 U
b100 [
b1100 /
b1100 Q
b1100 Z
bx %
bx O
bx ]
bx f
b11000101110001000110011 #
b11000101110001000110011 T
b11000101110001000110011 W
b1100 ,
b1100 :
b1100 Y
b1100 .
b1100 8
b1100 X
b1000 0
b1000 9
b1000 <
b1000 R
b1000 V
1!
#25
0!
#30
1M
b10 2
b10 L
b10 S
0*
b1 6
b1 ?
b1 K
1B
b100 b
b0 A
b100 a
b1100011 C
b10101 c
b11111111111100100000011111100100 3
b11111111111100100000011111100100 ;
b11111111111100100000011111100100 U
b11111111111100100000011111100100 [
b10000 /
b10000 Q
b10000 Z
b11111110010000100000101011100011 #
b11111110010000100000101011100011 T
b11111110010000100000101011100011 W
b11111111111100100000011111110000 ,
b11111111111100100000011111110000 :
b11111111111100100000011111110000 Y
b10000 .
b10000 8
b10000 X
b1100 0
b1100 9
b1100 <
b1100 R
b1100 V
1!
#35
0!
#40
b1 6
b1 ?
b1 K
0B
b111 b
b101 a
b10000 c
b101000100000100110 3
b101000100000100110 ;
b101000100000100110 U
b101000100000100110 [
b10100 /
b10100 Q
b10100 Z
bx '
bx >
bx e
b10011100101000100001100011 #
b10011100101000100001100011 T
b10011100101000100001100011 W
b101000100000110110 ,
b101000100000110110 :
b101000100000110110 Y
b10100 .
b10100 8
b10100 X
b10000 0
b10000 9
b10000 <
b10000 R
b10000 V
1!
#45
0!
#50
b0 )
b0 `
b0 d
b0 5
b0 @
b0 N
b0 ^
b0 6
b0 ?
b0 K
b0 b
b0 c
b0 a
b0 C
b0 3
b0 ;
b0 U
b0 [
b11000 /
b11000 Q
b11000 Z
b0 &
b0 =
b0 \
b0 #
b0 T
b0 W
b10100 ,
b10100 :
b10100 Y
b11000 .
b11000 8
b11000 X
b10100 0
b10100 9
b10100 <
b10100 R
b10100 V
b0 %
b0 O
b0 ]
b0 f
b0 '
b0 >
b0 e
1!
#55
0!
#60
b11100 /
b11100 Q
b11100 Z
b11000 ,
b11000 :
b11000 Y
b11100 .
b11100 8
b11100 X
b11000 0
b11000 9
b11000 <
b11000 R
b11000 V
1!
#65
0!
#70
b100000 /
b100000 Q
b100000 Z
b11100 ,
b11100 :
b11100 Y
b100000 .
b100000 8
b100000 X
b11100 0
b11100 9
b11100 <
b11100 R
b11100 V
1!
#75
0!
#80
1$
bx 6
bx ?
bx K
xB
bx b
bx A
bx a
bx C
bx c
bx0 3
bx0 ;
bx0 U
bx0 [
b100100 /
b100100 Q
b100100 Z
bx #
bx T
bx W
bx ,
bx :
bx Y
b100100 .
b100100 8
b100100 X
b100000 0
b100000 9
b100000 <
b100000 R
b100000 V
1!
#85
0!
#90
b101000 /
b101000 Q
b101000 Z
bx &
bx =
bx \
b101000 .
b101000 8
b101000 X
b100100 0
b100100 9
b100100 <
b100100 R
b100100 V
bx %
bx O
bx ]
bx f
bx '
bx >
bx e
1!
#95
0!
#100
b101100 /
b101100 Q
b101100 Z
b101100 .
b101100 8
b101100 X
b101000 0
b101000 9
b101000 <
b101000 R
b101000 V
1!
#105
0!
#110
b110000 /
b110000 Q
b110000 Z
b110000 .
b110000 8
b110000 X
b101100 0
b101100 9
b101100 <
b101100 R
b101100 V
1!
